[
	{
		"_index": "data_description",
		"_id": "SetGoalSetting",
		"_source": {
			"achievementid": "SetGoalSetting",
			"type": "general",
			"title": "Sett Et Mål",
			"description_achieved": "Sett et mål ved hjelp av målsettingsverktøyet.",
			"description": "Sett et mål ved hjelp av målsettingsverktøyet.",
			"image": "https://dvlxmvtyf5r6m.cloudfront.net/achievements/set-goal-setting.png",
			"language": "nb",
			"goal": 1,
			"goaltext": "Ufullstendig.",
			"description_type": "achievement"
		}
	},
	{
		"_index": "data_description",
		"_id": "SetSleepTool",
		"_source": {
			"achievementid": "SetSleepTool",
			"type": "general",
			"title": "Påminnelse om søvn",
			"description_achieved": "Lag en påminnelse om søvn ved hjelp av søvnverktøyet.",
			"description": "Lag en påminnelse om søvn ved hjelp av søvnverktøyet.",
			"image": "https://dvlxmvtyf5r6m.cloudfront.net/achievements/sleep-reminder.png",
			"language": "nb",
			"goal": 1,
			"goaltext": "Ufullstendig.",
			"description_type": "achievement"
		}
	},
	{
		"_index": "data_description",
		"_id": "UseMindfulness",
		"_source": {
			"achievementid": "UseMindfulness",
			"type": "general",
			"title": "Sesjon med Mindfulness",
			"description_achieved": "Fullført en sesjon med mindfulness.",
			"description": "Fullfør en sesjon med mindfulness.",
			"image": "https://dvlxmvtyf5r6m.cloudfront.net/achievements/mindfulness-completed.png",
			"language": "nb",
			"goal": 1,
			"goaltext": "Ufullstendig.",
			"description_type": "achievement"
		}
	},
	{
		"_index": "data_description",
		"_id": "QACompleted",
		"_source": {
			"achievementid": "QACompleted",
			"type": "general",
			"title": "Første tilpassing av planen",
			"description_achieved": "Første tilpassing av planen er fullført.",
			"description": "Fullfør første tilpassing av planen din.",
			"image": "https://dvlxmvtyf5r6m.cloudfront.net/achievements/qa-completed.png",
			"language": "nb",
			"goal": 1,
			"goaltext": "Ufullstendig.",
			"description_type": "achievement"
		}
	},
	{
		"_index": "data_description",
		"_id": "SessionCompleted",
		"_source": {
			"achievementid": "SessionCompleted",
			"type": "general",
			"title": "Introduksjon til selfBACK",
			"description_achieved": "Introduksjon til selfBACK er fullført.",
			"description": "Fullfør introduksjon til selfBACK.",
			"image": "https://dvlxmvtyf5r6m.cloudfront.net/achievements/session-completed.png",
			"language": "nb",
			"goal": 1,
			"goaltext": "Ufullstendig.",
			"description_type": "achievement"
		}
	},
	{
		"_index": "data_description",
		"_id": "EducationalCorrectQuiz1",
		"_source": {
			"achievementid": "EducationalCorrectQuiz1",
			"type": "educational",
			"title": "Korrekt svar på quiz",
			"description_achieved": "Korrekt svar på et quiz spørsmål.",
			"description": "Korrekt svar på et quiz spørsmål.",
			"image": "https://dvlxmvtyf5r6m.cloudfront.net/achievements/correct-quiz-1.png",
			"language": "nb",
			"goal": 1,
			"goaltext": "Fullført.",
			"description_type": "achievement"
		}
	},
	{
		"_index": "data_description",
		"_id": "EducationalCorrectQuiz3",
		"_source": {
			"achievementid": "EducationalCorrectQuiz3",
			"type": "educational",
			"title": "Korrekt svar på quiz",
			"description_achieved": "Korrekt svar på 3 quiz spørsmål.",
			"description": "Korrekt svar på 3 quiz spørsmål.",
			"image": "https://dvlxmvtyf5r6m.cloudfront.net/achievements/correct-quiz-3.png",
			"language": "nb",
			"goal": 3,
			"goaltext": "Fullført.",
			"description_type": "achievement"
		}
	},
	{
		"_index": "data_description",
		"_id": "EducationalCorrectQuiz7",
		"_source": {
			"achievementid": "EducationalCorrectQuiz7",
			"type": "educational",
			"title": "Korrekt svar på quiz",
			"description_achieved": "Korrekt svar på 7 quiz spørsmål.",
			"description": "Korrekt svar på 7 quiz spørsmål.",
			"image": "https://dvlxmvtyf5r6m.cloudfront.net/achievements/correct-quiz-7.png",
			"language": "nb",
			"goal": 7,
			"goaltext": "Fullført.",
			"description_type": "achievement"
		}
	},
	{
		"_index": "data_description",
		"_id": "EducationalCorrectQuiz14",
		"_source": {
			"achievementid": "EducationalCorrectQuiz14",
			"type": "educational",
			"title": "Korrekt svar på quiz",
			"description_achieved": "Korrekt svar på 14 quiz spørsmål.",
			"description": "Korrekt svar på 14 quiz spørsmål.",
			"image": "https://dvlxmvtyf5r6m.cloudfront.net/achievements/correct-quiz-14.png",
			"language": "nb",
			"goal": 14,
			"goaltext": "Fullført.",
			"description_type": "achievement"
		}
	},
	{
		"_index": "data_description",
		"_id": "EducationalCorrectQuiz25",
		"_source": {
			"achievementid": "EducationalCorrectQuiz25",
			"type": "educational",
			"title": "Korrekt svar på quiz",
			"description_achieved": "Korrekt svar på 25 quiz spørsmål.",
			"description": "Korrekt svar på 25 quiz spørsmål",
			"image": "https://dvlxmvtyf5r6m.cloudfront.net/achievements/correct-quiz-25.png",
			"language": "nb",
			"goal": 25,
			"goaltext": "Fullført.",
			"description_type": "achievement"
		}
	},
	{
		"_index": "data_description",
		"_id": "EducationalMaterialRead1",
		"_source": {
			"achievementid": "EducationalMaterialRead1",
			"type": "educational",
			"title": "Lest 'Godt å vite'",
			"description_achieved": "Lest en beskjed i 'Godt å vite'.",
			"description": "Lest en beskjed i 'Godt å vite'.",
			"image": "https://dvlxmvtyf5r6m.cloudfront.net/achievements/educational-read-1.png",
			"language": "nb",
			"goal": 1,
			"goaltext": "Fullført.",
			"description_type": "achievement"
		}
	},
	{
		"_index": "data_description",
		"_id": "EducationalMaterialRead3",
		"_source": {
			"achievementid": "EducationalMaterialRead3",
			"type": "educational",
			"title": "Lest 'Godt å vite'",
			"description_achieved": "Lest 3 beskjeder i 'Godt å vite'.",
			"description": "Lest 3 beskjeder i 'Godt å vite'.",
			"image": "https://dvlxmvtyf5r6m.cloudfront.net/achievements/educational-read-3.png",
			"language": "nb",
			"goal": 3,
			"goaltext": "Fullført.",
			"description_type": "achievement"
		}
	},
	{
		"_index": "data_description",
		"_id": "EducationalMaterialRead7",
		"_source": {
			"achievementid": "EducationalMaterialRead7",
			"type": "educational",
			"title": "Lest 'Godt å vite'",
			"description_achieved": "Lest 7 beskjeder i 'Godt å vite'.",
			"description": "Lest 7 beskjeder i 'Godt å vite'.",
			"image": "https://dvlxmvtyf5r6m.cloudfront.net/achievements/educational-read-7.png",
			"language": "nb",
			"goal": 7,
			"goaltext": "Fullført.",
			"description_type": "achievement"
		}
	},
	{
		"_index": "data_description",
		"_id": "EducationalMaterialRead14",
		"_source": {
			"achievementid": "EducationalMaterialRead14",
			"type": "educational",
			"title": "Lest 'Godt å vite'",
			"description_achieved": "Lest 14 beskjeder i 'Godt å vite'.",
			"description": "Lest 14 beskjeder i 'Godt å vite'.",
			"image": "https://dvlxmvtyf5r6m.cloudfront.net/achievements/educational-read-14.png",
			"language": "nb",
			"goal": 14,
			"goaltext": "Fullført.",
			"description_type": "achievement"
		}
	},
	{
		"_index": "data_description",
		"_id": "EducationalMaterialRead25",
		"_source": {
			"achievementid": "EducationalMaterialRead25",
			"type": "educational",
			"title": "Lest 'Godt å vite'",
			"description_achieved": "Lest 25 beskjeder i 'Godt å vite'.",
			"description": "Lest 25 beskjeder i 'Godt å vite'.",
			"image": "https://dvlxmvtyf5r6m.cloudfront.net/achievements/educational-read-25.png",
			"language": "nb",
			"goal": 25,
			"goaltext": "Fullført.",
			"description_type": "achievement"
		}
	},
	{
		"_index": "data_description",
		"_id": "EducationalMaterialRead40",
		"_source": {
			"achievementid": "EducationalMaterialRead40",
			"type": "educational",
			"title": "Lest 'Godt å vite'",
			"description_achieved": "Lest 40 beskjeder i 'Godt å vite'.",
			"description": "Lest 40 beskjeder i 'Godt å vite'.",
			"image": "https://dvlxmvtyf5r6m.cloudfront.net/achievements/educational-read-40.png",
			"language": "nb",
			"goal": 40,
			"goaltext": "Fullført.",
			"description_type": "achievement"
		}
	},
	{
		"_index": "data_description",
		"_id": "EducationalMaterialRead60",
		"_source": {
			"achievementid": "EducationalMaterialRead60",
			"type": "educational",
			"title": "Lest 'Godt å vite'",
			"description_achieved": "Lest 60 beskjeder i 'Godt å vite'.",
			"description": "Lest 60 beskjeder i 'Godt å vite'.",
			"image": "https://dvlxmvtyf5r6m.cloudfront.net/achievements/educational-read-60.png",
			"language": "nb",
			"goal": 60,
			"goaltext": "Fullført.",
			"description_type": "achievement"
		}
	},
	{
		"_index": "data_description",
		"_id": "EducationalMaterialRead80",
		"_source": {
			"achievementid": "EducationalMaterialRead80",
			"type": "educational",
			"title": "Lest 'Godt å vite'",
			"description_achieved": "Lest 80 beskjeder i 'Godt å vite'.",
			"description": "Lest 80 beskjeder i 'Godt å vite'.",
			"image": "https://dvlxmvtyf5r6m.cloudfront.net/achievements/educational-read-80.png",
			"language": "nb",
			"goal": 80,
			"goaltext": "Fullført.",
			"description_type": "achievement"
		}
	},
	{
		"_index": "data_description",
		"_id": "EducationalMaterialRead100",
		"_source": {
			"achievementid": "EducationalMaterialRead100",
			"type": "educational",
			"title": "Lest 'Godt å vite'",
			"description_achieved": "Lest 100 beskjeder i 'Godt å vite'.",
			"description": "Lest 100 beskjeder i 'Godt å vite'.",
			"image": "https://dvlxmvtyf5r6m.cloudfront.net/achievements/educational-read-100.png",
			"language": "nb",
			"goal": 100,
			"goaltext": "Fullført.",
			"description_type": "achievement"
		}
	},
	{
		"_index": "data_description",
		"_id": "DailyActivitiesCompleted1",
		"_source": {
			"achievementid": "DailyActivitiesCompleted1",
			"type": "general",
			"title": "Daglig måloppnåelse",
			"description_achieved": "Alle tre aktiviteter er fullført på samme dag for første gang.",
			"description": "Gjennomfør alle de tre aktivitetene på samme dag for første gang.",
			"image": "https://dvlxmvtyf5r6m.cloudfront.net/achievements/daily-activities-completed-1.png",
			"language": "nb",
			"goal": 1,
			"goaltext": "Fullført",
			"description_type": "achievement"
		}
	},
	{
		"_index": "data_description",
		"_id": "DailyActivitiesCompleted3",
		"_source": {
			"achievementid": "DailyActivitiesCompleted3",
			"type": "general",
			"title": "Daglig måloppnåelse",
			"description_achieved": "Alle tre aktiviteter er fullført på samme dag for 3. gang.",
			"description": "Gjennomfør alle de tre aktivitetene på samme dag for 3. gang.",
			"image": "https://dvlxmvtyf5r6m.cloudfront.net/achievements/daily-activities-completed-2.png",
			"language": "nb",
			"goal": 3,
			"goaltext": "Fullført",
			"description_type": "achievement"
		}
	},
	{
		"_index": "data_description",
		"_id": "DailyActivitiesCompleted7",
		"_source": {
			"achievementid": "DailyActivitiesCompleted7",
			"type": "general",
			"title": "Daglig måloppnåelse",
			"description_achieved": "Alle tre aktiviteter er fullført på samme dag for 7. gang.",
			"description": "Gjennomfør alle de tre aktivitetene på samme dag for 7. gang.",
			"image": "https://dvlxmvtyf5r6m.cloudfront.net/achievements/daily-activities-completed-3.png",
			"language": "nb",
			"goal": 7,
			"goaltext": "Fullført",
			"description_type": "achievement"
		}
	},
	{
		"_index": "data_description",
		"_id": "DailyActivitiesCompleted14",
		"_source": {
			"achievementid": "DailyActivitiesCompleted14",
			"type": "general",
			"title": "Daglig måloppnåelse",
			"description_achieved": "Alle tre aktiviteter er fullført på samme dag for 14. gang.",
			"description": "Gjennomfør alle de tre aktivitetene på samme dag for 14. gang.",
			"image": "https://dvlxmvtyf5r6m.cloudfront.net/achievements/daily-activities-completed-4.png",
			"language": "nb",
			"goal": 14,
			"goaltext": "Fullført",
			"description_type": "achievement"
		}
	},
	{
		"_index": "data_description",
		"_id": "DailyActivitiesCompleted25",
		"_source": {
			"achievementid": "DailyActivitiesCompleted25",
			"type": "general",
			"title": "Daglig måloppnåelse",
			"description_achieved": "Alle tre aktiviteter er fullført på samme dag for 25. gang.",
			"description": "Gjennomfør alle de tre aktivitetene på samme dag for 25. gang.",
			"image": "https://dvlxmvtyf5r6m.cloudfront.net/achievements/daily-activities-completed-5.png",
			"language": "nb",
			"goal": 25,
			"goaltext": "Fullført",
			"description_type": "achievement"
		}
	},
	{
		"_index": "data_description",
		"_id": "DailyActivitiesCompleted40",
		"_source": {
			"achievementid": "DailyActivitiesCompleted40",
			"type": "general",
			"title": "Daglig måloppnåelse",
			"description_achieved": "Alle tre aktiviteter er fullført på samme dag for 40. gang.",
			"description": "Gjennomfør alle de tre aktivitetene på samme dag for 40. gang.",
			"image": "https://dvlxmvtyf5r6m.cloudfront.net/achievements/daily-activities-completed-6.png",
			"language": "nb",
			"goal": 40,
			"goaltext": "Fullført",
			"description_type": "achievement"
		}
	},
	{
		"_index": "data_description",
		"_id": "DailyGoalSteps1",
		"_source": {
			"achievementid": "DailyGoalSteps1",
			"type": "physical",
			"title": "Nå målet ditt",
			"description_achieved": "Det daglige målet for antall skritt er nådd for første gang.",
			"description": "Nå ditt daglige mål for antall skritt for første gang.",
			"image": "https://dvlxmvtyf5r6m.cloudfront.net/achievements/daily-goal-steps-1.png",
			"language": "nb",
			"goal": 1,
			"goaltext": "Fullført",
			"description_type": "achievement"
		}
	},
	{
		"_index": "data_description",
		"_id": "DailyGoalSteps3",
		"_source": {
			"achievementid": "DailyGoalSteps3",
			"type": "physical",
			"title": "Nå målet ditt",
			"description_achieved": "Det daglige målet for antall skritt er nådd 3 ganger.",
			"description": "Nå ditt daglige mål for antall skritt 3 ganger.",
			"image": "https://dvlxmvtyf5r6m.cloudfront.net/achievements/daily-goal-steps-3.png",
			"language": "nb",
			"goal": 3,
			"goaltext": "Fullført",
			"description_type": "achievement"
		}
	},
	{
		"_index": "data_description",
		"_id": "DailyGoalSteps7",
		"_source": {
			"achievementid": "DailyGoalSteps7",
			"type": "physical",
			"title": "Nå målet ditt",
			"description_achieved": "Det daglige målet for antall skritt er nådd 7 ganger.",
			"description": "Nå ditt daglige mål for antall skritt 7 ganger.",
			"image": "https://dvlxmvtyf5r6m.cloudfront.net/achievements/daily-goal-steps-7.png",
			"language": "nb",
			"goal": 7,
			"goaltext": "Fullført",
			"description_type": "achievement"
		}
	},
	{
		"_index": "data_description",
		"_id": "DailyGoalSteps14",
		"_source": {
			"achievementid": "DailyGoalSteps14",
			"type": "physical",
			"title": "Nå målet ditt",
			"description_achieved": "Det daglige målet for antall skritt er nådd 14 ganger.",
			"description": "Nå ditt daglige mål for antall skritt 14 ganger.",
			"image": "https://dvlxmvtyf5r6m.cloudfront.net/achievements/daily-goal-steps-14.png",
			"language": "nb",
			"goal": 14,
			"goaltext": "Fullført",
			"description_type": "achievement"
		}
	},
	{
		"_index": "data_description",
		"_id": "DailyGoalSteps25",
		"_source": {
			"achievementid": "DailyGoalSteps25",
			"type": "physical",
			"title": "Nå målet ditt",
			"description_achieved": "Det daglige målet for antall skritt er nådd 25 ganger.",
			"description": "Nå ditt daglige mål for antall skritt 25 ganger.",
			"image": "https://dvlxmvtyf5r6m.cloudfront.net/achievements/daily-goal-steps-25.png",
			"language": "nb",
			"goal": 25,
			"goaltext": "Fullført",
			"description_type": "achievement"
		}
	},
	{
		"_index": "data_description",
		"_id": "DailyGoalSteps40",
		"_source": {
			"achievementid": "DailyGoalSteps40",
			"type": "physical",
			"title": "Nå målet ditt",
			"description_achieved": "Det daglige målet for antall skritt er nådd 40 ganger.",
			"description": "Nå ditt daglige mål for antall skritt 40 ganger.",
			"image": "https://dvlxmvtyf5r6m.cloudfront.net/achievements/daily-goal-steps-40.png",
			"language": "nb",
			"goal": 40,
			"goaltext": "Fullført",
			"description_type": "achievement"
		}
	},
	{
		"_index": "data_description",
		"_id": "DailyGoalSteps60",
		"_source": {
			"achievementid": "DailyGoalSteps60",
			"type": "physical",
			"title": "Nå målet ditt",
			"description_achieved": "Det daglige målet for antall skritt er nådd 60 ganger.",
			"description": "Nå ditt daglige mål for antall skritt 60 ganger.",
			"image": "https://dvlxmvtyf5r6m.cloudfront.net/achievements/daily-goal-steps-60.png",
			"language": "nb",
			"goal": 60,
			"goaltext": "Fullført",
			"description_type": "achievement"
		}
	},
	{
		"_index": "data_description",
		"_id": "DailyGoalSteps80",
		"_source": {
			"achievementid": "DailyGoalSteps80",
			"type": "physical",
			"title": "Nå målet ditt",
			"description_achieved": "Det daglige målet for antall skritt er nådd 80 ganger.",
			"description": "Nå ditt daglige mål for antall skritt 80 ganger.",
			"image": "https://dvlxmvtyf5r6m.cloudfront.net/achievements/daily-goal-steps-80.png",
			"language": "nb",
			"goal": 80,
			"goaltext": "Fullført",
			"description_type": "achievement"
		}
	},
	{
		"_index": "data_description",
		"_id": "DailyGoalSteps100",
		"_source": {
			"achievementid": "DailyGoalSteps100",
			"type": "physical",
			"title": "Nå målet ditt",
			"description_achieved": "Det daglige målet for antall skritt er nådd 100 ganger.",
			"description": "Nå ditt daglige mål for antall skritt 100 ganger.",
			"image": "https://dvlxmvtyf5r6m.cloudfront.net/achievements/daily-goal-steps-100.png",
			"language": "nb",
			"goal": 100,
			"goaltext": "Fullført",
			"description_type": "achievement"
		}
	},
	{
		"_index": "data_description",
		"_id": "FullCompletedWeekSteps",
		"_source": {
			"achievementid": "FullCompletedWeekSteps",
			"type": "physical",
			"title": "Langsiktige mål",
			"description_achieved": "Det daglige målet for antall skritt er nådd hver dag i en hel uke.",
			"description": "Nå ditt daglige mål for antall skritt hver dag for en hel uke.",
			"image": "https://dvlxmvtyf5r6m.cloudfront.net/achievements/full-completed-week-steps.png",
			"language": "nb",
			"goal": 1,
			"goaltext": "Fullført",
			"description_type": "achievement"
		}
	},
	{
		"_index": "data_description",
		"_id": "RowCompletedSteps3",
		"_source": {
			"achievementid": "RowCompletedSteps3",
			"type": "physical",
			"title": "Utfordring for antall skritt",
			"description_achieved": "Det daglige målet for antall skritt er nådd tre ganger på rad.",
			"description": "Nå ditt daglige mål for antall skritt tre ganger på rad.",
			"image": "https://dvlxmvtyf5r6m.cloudfront.net/achievements/row-completed-steps-3.png",
			"language": "nb",
			"goal": 3,
			"goaltext": "Fullført",
			"description_type": "achievement"
		}
	},
	{
		"_index": "data_description",
		"_id": "RowCompletedSteps7",
		"_source": {
			"achievementid": "RowCompletedSteps7",
			"type": "physical",
			"title": "Utfordring for antall skritt",
			"description_achieved": "Det daglige målet for antall skritt er nådd syv ganger på rad.",
			"description": "Nå ditt daglige mål for antall skritt syv ganger på rad.",
			"image": "https://dvlxmvtyf5r6m.cloudfront.net/achievements/row-completed-steps-7.png",
			"language": "nb",
			"goal": 7,
			"goaltext": "Fullført",
			"description_type": "achievement"
		}
	},
	{
		"_index": "data_description",
		"_id": "RowCompletedSteps14",
		"_source": {
			"achievementid": "RowCompletedSteps14",
			"type": "physical",
			"title": "Utfordring for antall skritt",
			"description_achieved": "Det daglige målet for antall skritt er nådd fjorten ganger på rad.",
			"description": "Nå ditt daglige mål for antall skritt fjorten ganger på rad.",
			"image": "https://dvlxmvtyf5r6m.cloudfront.net/achievements/row-completed-steps-14.png",
			"language": "nb",
			"goal": 14,
			"goaltext": "Fullført",
			"description_type": "achievement"
		}
	},
	{
		"_index": "data_description",
		"_id": "RowCompletedSteps25",
		"_source": {
			"achievementid": "RowCompletedSteps25",
			"type": "physical",
			"title": "Utfordring for antall skritt",
			"description_achieved": "Det daglige målet for antall skritt er nådd 25 ganger på rad.",
			"description": "Nå ditt daglige mål for antall skritt 25 ganger på rad.",
			"image": "https://dvlxmvtyf5r6m.cloudfront.net/achievements/row-completed-steps-25.png",
			"language": "nb",
			"goal": 25,
			"goaltext": "Fullført",
			"description_type": "achievement"
		}
	},
	{
		"_index": "data_description",
		"_id": "RowCompletedSteps40",
		"_source": {
			"achievementid": "RowCompletedSteps40",
			"type": "physical",
			"title": "Utfordring for antall skritt",
			"description_achieved": "Det daglige målet for antall skritt er nådd 40 ganger på rad.",
			"description": "Nå ditt daglige mål for antall skritt 40 ganger på rad.",
			"image": "https://dvlxmvtyf5r6m.cloudfront.net/achievements/row-completed-steps-40.png",
			"language": "nb",
			"goal": 40,
			"goaltext": "Fullført",
			"description_type": "achievement"
		}
	},
	{
		"_index": "data_description",
		"_id": "DailyRecordSteps10",
		"_source": {
			"achievementid": "DailyRecordSteps10",
			"type": "physical",
			"title": "Press grensene",
			"description_achieved": "Gått 10.000 skritt på en dag.",
			"description": "Gå 10.000 skritt på en dag.",
			"image": "https://dvlxmvtyf5r6m.cloudfront.net/achievements/daily-record-steps-10.png",
			"language": "nb",
			"goal": 10000,
			"goaltext": "Fullført",
			"description_type": "achievement"
		}
	},
	{
		"_index": "data_description",
		"_id": "DailyRecordSteps12",
		"_source": {
			"achievementid": "DailyRecordSteps12",
			"type": "physical",
			"title": "Press grensene",
			"description_achieved": "Gått 12.000 skritt på en dag.",
			"description": "Gå 12.000 skritt på en dag.",
			"image": "https://dvlxmvtyf5r6m.cloudfront.net/achievements/daily-record-steps-12.png",
			"language": "nb",
			"goal": 12000,
			"goaltext": "Fullført",
			"description_type": "achievement"
		}
	},
	{
		"_index": "data_description",
		"_id": "DailyRecordSteps14",
		"_source": {
			"achievementid": "DailyRecordSteps14",
			"type": "physical",
			"title": "Press grensene",
			"description_achieved": "Gått 14.000 skritt på en dag.",
			"description": "Gå 14.000 skritt på en dag.",
			"image": "https://dvlxmvtyf5r6m.cloudfront.net/achievements/daily-record-steps-14.png",
			"language": "nb",
			"goal": 14000,
			"goaltext": "Fullført",
			"description_type": "achievement"
		}
	},
	{
		"_index": "data_description",
		"_id": "DailyRecordSteps16",
		"_source": {
			"achievementid": "DailyRecordSteps16",
			"type": "physical",
			"title": "Press grensene",
			"description_achieved": "Gått 16.000 skritt på en dag.",
			"description": "Gå 16.000 skritt på en dag.",
			"image": "https://dvlxmvtyf5r6m.cloudfront.net/achievements/daily-record-steps-16.png",
			"language": "nb",
			"goal": 16000,
			"goaltext": "Fullført",
			"description_type": "achievement"
		}
	},
	{
		"_index": "data_description",
		"_id": "DailyRecordSteps18",
		"_source": {
			"achievementid": "DailyRecordSteps18",
			"type": "physical",
			"title": "Press grensene",
			"description_achieved": "Gått 18.000 skritt på en dag.",
			"description": "Gå 18.000 skritt på en dag.",
			"image": "https://dvlxmvtyf5r6m.cloudfront.net/achievements/daily-record-steps-18.png",
			"language": "nb",
			"goal": 18000,
			"goaltext": "Fullført",
			"description_type": "achievement"
		}
	},
	{
		"_index": "data_description",
		"_id": "DailyRecordSteps20",
		"_source": {
			"achievementid": "DailyRecordSteps20",
			"type": "physical",
			"title": "Press grensene",
			"description_achieved": "Gått 20.000 skritt på en dag.",
			"description": "Gå 20.000 skritt på en dag.",
			"image": "https://dvlxmvtyf5r6m.cloudfront.net/achievements/daily-record-steps-20.png",
			"language": "nb",
			"goal": 20000,
			"goaltext": "Fullført",
			"description_type": "achievement"
		}
	},
	{
		"_index": "data_description",
		"_id": "TotalSteps50",
		"_source": {
			"achievementid": "TotalSteps50",
			"type": "physical",
			"title": "Totalt antall skritt",
			"description_achieved": "Totalt har du nådd 50.000 skritt med bruk av selfBACK.",
			"description": "Nå et totalt antall skritt på 50.000 med bruk av selfBACK.",
			"image": "https://dvlxmvtyf5r6m.cloudfront.net/achievements/total-steps-50.png",
			"language": "nb",
			"goal": 50000,
			"goaltext": "Fullført",
			"description_type": "achievement"
		}
	},
	{
		"_index": "data_description",
		"_id": "TotalSteps100",
		"_source": {
			"achievementid": "TotalSteps100",
			"type": "physical",
			"title": "Totalt antall skritt",
			"description_achieved": "Totalt har du nådd 100.000 skritt med bruk av selfBACK.",
			"description": "Nå et totalt antall skritt på 100.000 med bruk av selfBACK.",
			"image": "https://dvlxmvtyf5r6m.cloudfront.net/achievements/total-steps-100.png",
			"language": "nb",
			"goal": 100000,
			"goaltext": "Fullført",
			"description_type": "achievement"
		}
	},
	{
		"_index": "data_description",
		"_id": "TotalSteps200",
		"_source": {
			"achievementid": "TotalSteps200",
			"type": "physical",
			"title": "Totalt antall skritt",
			"description_achieved": "Totalt har du nådd 200.000 skritt med bruk av selfBACK.",
			"description": "Nå et totalt antall skritt på 200.000 med bruk av selfBACK.",
			"image": "https://dvlxmvtyf5r6m.cloudfront.net/achievements/total-steps-200.png",
			"language": "nb",
			"goal": 200000,
			"goaltext": "Fullført",
			"description_type": "achievement"
		}
	},
	{
		"_index": "data_description",
		"_id": "TotalSteps400",
		"_source": {
			"achievementid": "TotalSteps400",
			"type": "physical",
			"title": "Totalt antall skritt",
			"description_achieved": "Totalt har du nådd 400.000 skritt med bruk av selfBACK.",
			"description": "Nå et totalt antall skritt på 400.000 med bruk av selfBACK.",
			"image": "https://dvlxmvtyf5r6m.cloudfront.net/achievements/total-steps-400.png",
			"language": "nb",
			"goal": 400000,
			"goaltext": "Fullført",
			"description_type": "achievement"
		}
	},
	{
		"_index": "data_description",
		"_id": "TotalSteps600",
		"_source": {
			"achievementid": "TotalSteps600",
			"type": "physical",
			"title": "Totalt antall skritt",
			"description_achieved": "Totalt har du nådd 600.000 skritt med bruk av selfBACK.",
			"description": "Nå et totalt antall skritt på 600.000 med bruk av selfBACK.",
			"image": "https://dvlxmvtyf5r6m.cloudfront.net/achievements/total-steps-600.png",
			"language": "nb",
			"goal": 600000,
			"goaltext": "Fullført",
			"description_type": "achievement"
		}
	},
	{
		"_index": "data_description",
		"_id": "TotalSteps800",
		"_source": {
			"achievementid": "TotalSteps800",
			"type": "physical",
			"title": "Totalt antall skritt",
			"description_achieved": "Totalt har du nådd 800.000 skritt med bruk av selfBACK.",
			"description": "Nå et totalt antall skritt på 800.000 med bruk av selfBACK.",
			"image": "https://dvlxmvtyf5r6m.cloudfront.net/achievements/total-steps-800.png",
			"language": "nb",
			"goal": 800000,
			"goaltext": "Fullført",
			"description_type": "achievement"
		}
	},
	{
		"_index": "data_description",
		"_id": "TotalSteps1000",
		"_source": {
			"achievementid": "TotalSteps1000",
			"type": "physical",
			"title": "Totalt antall skritt",
			"description_achieved": "Totalt har du nådd 1.000.000 skritt med bruk av selfBACK.",
			"description": "Nå et totalt antall skritt på 1.000.000 med bruk av selfBACK.",
			"image": "https://dvlxmvtyf5r6m.cloudfront.net/achievements/total-steps-1000.png",
			"language": "nb",
			"goal": 1000000,
			"goaltext": "Fullført",
			"description_type": "achievement"
		}
	},
	{
		"_index": "data_description",
		"_id": "Marathon",
		"_source": {
			"achievementid": "Marathon",
			"type": "physical",
			"title": "Antikkens Hellas",
			"description_achieved": "Ditt totale antall skritt tilsvarer nå en maraton!",
			"description": "Ta like mange skritt tilsvarende en maraton!",
			"image": "https://dvlxmvtyf5r6m.cloudfront.net/achievements/marathon.png",
			"language": "nb",
			"goal": -1,
			"goaltext": "Fullført",
			"description_type": "achievement"
		}
	},
	{
		"_index": "data_description",
		"_id": "AverageStepsWeek5",
		"_source": {
			"achievementid": "AverageStepsWeek5",
			"type": "physical",
			"title": "Ukentlig aktivitet",
			"description_achieved": "Denne uken har du i gjennomsnitt gått 5.000 skritt hver dag.",
			"description": "Gå i gjennomsnitt 5.000 skritt hver dag i en uke.",
			"image": "https://dvlxmvtyf5r6m.cloudfront.net/achievements/average-steps-week-5.png",
			"language": "nb",
			"goal": 5000,
			"goaltext": "Fullført",
			"description_type": "achievement"
		}
	},
	{
		"_index": "data_description",
		"_id": "AverageStepsWeek6",
		"_source": {
			"achievementid": "AverageStepsWeek6",
			"type": "physical",
			"title": "Ukentlig aktivitet",
			"description_achieved": "Denne uken har du i gjennomsnitt gått 6.000 skritt hver dag.",
			"description": "Gå i gjennomsnitt 6.000 skritt hver dag i en uke.",
			"image": "https://dvlxmvtyf5r6m.cloudfront.net/achievements/average-steps-week-6.png",
			"language": "nb",
			"goal": 6000,
			"goaltext": "Fullført",
			"description_type": "achievement"
		}
	},
	{
		"_index": "data_description",
		"_id": "AverageStepsWeek8",
		"_source": {
			"achievementid": "AverageStepsWeek8",
			"type": "physical",
			"title": "Ukentlig aktivitet",
			"description_achieved": "Denne uken har du i gjennomsnitt gått 8.000 skritt hver dag.",
			"description": "Gå i gjennomsnitt 8.000 skritt hver dag i en uke.",
			"image": "https://dvlxmvtyf5r6m.cloudfront.net/achievements/average-steps-week-8.png",
			"language": "nb",
			"goal": 8000,
			"goaltext": "Fullført",
			"description_type": "achievement"
		}
	},
	{
		"_index": "data_description",
		"_id": "AverageStepsWeek10",
		"_source": {
			"achievementid": "AverageStepsWeek10",
			"type": "physical",
			"title": "Ukentlig aktivitet",
			"description_achieved": "Denne uken har du i gjennomsnitt gått 10.000 skritt hver dag.",
			"description": "Gå i gjennomsnitt 10.000 skritt hver dag i en uke.",
			"image": "https://dvlxmvtyf5r6m.cloudfront.net/achievements/average-steps-week-10.png",
			"language": "nb",
			"goal": 10000,
			"goaltext": "Fullført",
			"description_type": "achievement"
		}
	},
	{
		"_index": "data_description",
		"_id": "AverageStepsWeek12",
		"_source": {
			"achievementid": "AverageStepsWeek12",
			"type": "physical",
			"title": "Ukentlig aktivitet",
			"description_achieved": "Denne uken har du i gjennomsnitt gått 12.000 skritt hver dag.",
			"description": "Gå i gjennomsnitt 12.000 skritt hver dag i en uke.",
			"image": "https://dvlxmvtyf5r6m.cloudfront.net/achievements/average-steps-week-12.png",
			"language": "nb",
			"goal": 12000,
			"goaltext": "Fullført",
			"description_type": "achievement"
		}
	},
	{
		"_index": "data_description",
		"_id": "ExerciseDaysCompleted1",
		"_source": {
			"achievementid": "ExerciseDaysCompleted1",
			"type": "exercise",
			"title": "Øvelsesprogram",
			"description_achieved": "Du har fullført din første dag med øvelsesprogrammet.",
			"description": "Fullfør din første dag med øvelsesprogrammet.",
			"image": "https://dvlxmvtyf5r6m.cloudfront.net/achievements/exercise-days-completed-1.png",
			"language": "nb",
			"goal": 1,
			"goaltext": "Fullført",
			"description_type": "achievement"
		}
	},
	{
		"_index": "data_description",
		"_id": "ExerciseDaysCompleted3",
		"_source": {
			"achievementid": "ExerciseDaysCompleted3",
			"type": "exercise",
			"title": "Øvelsesprogram",
			"description_achieved": "Du har fullført din 3. dag med øvelsesprogrammet.",
			"description": "Fullfør din 3. dag med øvelsesprogrammet.",
			"image": "https://dvlxmvtyf5r6m.cloudfront.net/achievements/exercise-days-completed-3.png",
			"language": "nb",
			"goal": 3,
			"goaltext": "Fullført",
			"description_type": "achievement"
		}
	},
	{
		"_index": "data_description",
		"_id": "ExerciseDaysCompleted7",
		"_source": {
			"achievementid": "ExerciseDaysCompleted7",
			"type": "exercise",
			"title": "Øvelsesprogram",
			"description_achieved": "Du har fullført din 7. dag med øvelsesprogrammet.",
			"description": "Fullfør din 7. dag med øvelsesprogrammet.",
			"image": "https://dvlxmvtyf5r6m.cloudfront.net/achievements/exercise-days-completed-7.png",
			"language": "nb",
			"goal": 7,
			"goaltext": "Fullført",
			"description_type": "achievement"
		}
	},
	{
		"_index": "data_description",
		"_id": "ExerciseDaysCompleted14",
		"_source": {
			"achievementid": "ExerciseDaysCompleted14",
			"type": "exercise",
			"title": "Øvelsesprogram",
			"description_achieved": "Du har fullført din 14. dag med øvelsesprogrammet.",
			"description": "Fullfør din 14. dag med øvelsesprogrammet.",
			"image": "https://dvlxmvtyf5r6m.cloudfront.net/achievements/exercise-days-completed-14.png",
			"language": "nb",
			"goal": 14,
			"goaltext": "Fullført",
			"description_type": "achievement"
		}
	},
	{
		"_index": "data_description",
		"_id": "ExerciseDaysCompleted25",
		"_source": {
			"achievementid": "ExerciseDaysCompleted25",
			"type": "exercise",
			"title": "Øvelsesprogram",
			"description_achieved": "Du har fullført din 25. dag med øvelsesprogrammet.",
			"description": "Fullfør din 25. dag med øvelsesprogrammet.",
			"image": "https://dvlxmvtyf5r6m.cloudfront.net/achievements/exercise-days-completed-25.png",
			"language": "nb",
			"goal": 25,
			"goaltext": "Fullført",
			"description_type": "achievement"
		}
	},
	{
		"_index": "data_description",
		"_id": "ExerciseDaysCompleted40",
		"_source": {
			"achievementid": "ExerciseDaysCompleted40",
			"type": "exercise",
			"title": "Øvelsesprogram",
			"description_achieved": "Du har fullført din 40. dag med øvelsesprogrammet.",
			"description": "Fullfør din 40. dag med øvelsesprogrammet.",
			"image": "https://dvlxmvtyf5r6m.cloudfront.net/achievements/exercise-days-completed-40.png",
			"language": "nb",
			"goal": 40,
			"goaltext": "Fullført",
			"description_type": "achievement"
		}
	},
	{
		"_index": "data_description",
		"_id": "ExerciseDaysCompleted60",
		"_source": {
			"achievementid": "ExerciseDaysCompleted60",
			"type": "exercise",
			"title": "Øvelsesprogram",
			"description_achieved": "Du har fullført din 60. dag med øvelsesprogrammet.",
			"description": "Fullfør din 60. dag med øvelsesprogrammet.",
			"image": "https://dvlxmvtyf5r6m.cloudfront.net/achievements/exercise-days-completed-60.png",
			"language": "nb",
			"goal": 60,
			"goaltext": "Fullført",
			"description_type": "achievement"
		}
	},
	{
		"_index": "data_description",
		"_id": "ExerciseDaysCompleted80",
		"_source": {
			"achievementid": "ExerciseDaysCompleted80",
			"type": "exercise",
			"title": "Øvelsesprogram",
			"description_achieved": "Du har fullført din 80. dag med øvelsesprogrammet.",
			"description": "Fullfør din 80. dag med øvelsesprogrammet.",
			"image": "https://dvlxmvtyf5r6m.cloudfront.net/achievements/exercise-days-completed-80.png",
			"language": "nb",
			"goal": 80,
			"goaltext": "Fullført",
			"description_type": "achievement"
		}
	},
	{
		"_index": "data_description",
		"_id": "ExerciseDaysCompleted100",
		"_source": {
			"achievementid": "ExerciseDaysCompleted100",
			"type": "exercise",
			"title": "Øvelsesprogram",
			"description_achieved": "Du har fullført din 100. dag med øvelsesprogrammet.",
			"description": "Fullfør din 100. dag med øvelsesprogrammet.",
			"image": "https://dvlxmvtyf5r6m.cloudfront.net/achievements/exercise-days-completed-100.png",
			"language": "nb",
			"goal": 100,
			"goaltext": "Fullført",
			"description_type": "achievement"
		}
	},
	{
		"_index": "data_description",
		"_id": "EducationalQuizAnswers",
		"_source": {
			"achievementid": "EducationalQuizAnswers",
			"type": "stats",
			"title": "Kunnskapsquiz besvart",
			"description": "",
			"image": "https://dvlxmvtyf5r6m.cloudfront.net/achievements/educational-quiz-answers.png",
			"language": "nb",
			"goal": -1,
			"goaltext": "Kunnskapsquiz besvart",
			"description_type": "achievement"
		}
	},
	{
		"_index": "data_description",
		"_id": "TotalDistanceKm",
		"_source": {
			"achievementid": "TotalDistanceKm",
			"type": "stats",
			"title": "Antall kilometer gått med selfBACK",
			"description": "Antall kilometer du har gått fra du startet med selfBACK.",
			"image": "https://dvlxmvtyf5r6m.cloudfront.net/achievements/total-distance-km.png",
			"language": "nb",
			"goal": -1,
			"goaltext": "Kilometer gått",
			"description_type": "achievement"
		}
	},
	{
		"_index": "data_description",
		"_id": "EducationalRead",
		"_source": {
			"achievementid": "EducationalRead",
			"type": "stats",
			"title": "Antall kunnskapsmeldinger lest",
			"description": "Totalt antall kunnskapsmeldinger lest",
			"image": "https://dvlxmvtyf5r6m.cloudfront.net/achievements/educational-read.png",
			"language": "nb",
			"goal": -1,
			"goaltext": "Kunnskapsmeldinger lest",
			"description_type": "achievement"
		}
	},
	{
		"_index": "data_description",
		"_id": "ExercisesCompleted",
		"_source": {
			"achievementid": "ExercisesCompleted",
			"type": "stats",
			"title": "Antall fullførte øvelser",
			"description": "Totalt antall fullførte øvelser.",
			"image": "https://dvlxmvtyf5r6m.cloudfront.net/achievements/exercises-done.png",
			"language": "nb",
			"goal": -1,
			"goaltext": "Fullførte øvelser",
			"description_type": "achievement"
		}
	}
]